setup.py
py_ibm/__init__.py
py_ibm/agent.py
py_ibm/topology.py
py_ibm/world.py
py_ibm.egg-info/PKG-INFO
py_ibm.egg-info/SOURCES.txt
py_ibm.egg-info/dependency_links.txt
py_ibm.egg-info/not-zip-safe
py_ibm.egg-info/requires.txt
py_ibm.egg-info/top_level.txt