Metadata-Version: 1.0
Name: py-ibm
Version: 0.1.1
Summary: Resources for building individual-based models
Home-page: http://github.com/fsfrazao/Py_IBM
Author: Fabio Frazao
Author-email: fsfrazao@gmail.com
License: GNU General Public License v3.0
Platform: UNKNOWN
